orcheo/__init__.py
orcheo/persistence.py
orcheo/py.typed
orcheo/agentensor/__init__.py
orcheo/agentensor/checkpoints.py
orcheo/agentensor/evaluation.py
orcheo/agentensor/prompts.py
orcheo/agentensor/training.py
orcheo/config/__init__.py
orcheo/config/app_settings.py
orcheo/config/chatkit_rate_limit_settings.py
orcheo/config/defaults.py
orcheo/config/loader.py
orcheo/config/types.py
orcheo/config/vault_settings.py
orcheo/edges/__init__.py
orcheo/edges/base.py
orcheo/edges/branching.py
orcheo/edges/conditions.py
orcheo/edges/registry.py
orcheo/graph/__init__.py
orcheo/graph/builder.py
orcheo/graph/conditional.py
orcheo/graph/edges.py
orcheo/graph/normalization.py
orcheo/graph/parallel.py
orcheo/graph/state.py
orcheo/graph/ingestion/__init__.py
orcheo/graph/ingestion/config.py
orcheo/graph/ingestion/exceptions.py
orcheo/graph/ingestion/loader.py
orcheo/graph/ingestion/sandbox.py
orcheo/graph/ingestion/summary.py
orcheo/models/__init__.py
orcheo/models/base.py
orcheo/models/credential_crypto.py
orcheo/models/credential_health.py
orcheo/models/credential_metadata.py
orcheo/models/credential_oauth.py
orcheo/models/credential_scope.py
orcheo/models/credential_templates.py
orcheo/models/secret_governance.py
orcheo/models/workflow.py
orcheo/models/workflow_entities.py
orcheo/nodes/__init__.py
orcheo/nodes/agentensor.py
orcheo/nodes/ai.py
orcheo/nodes/base.py
orcheo/nodes/code.py
orcheo/nodes/communication.py
orcheo/nodes/debug.py
orcheo/nodes/javascript_sandbox.py
orcheo/nodes/mongodb.py
orcheo/nodes/python_sandbox.py
orcheo/nodes/registry.py
orcheo/nodes/rss.py
orcheo/nodes/slack.py
orcheo/nodes/state_utils.py
orcheo/nodes/storage.py
orcheo/nodes/sub_workflow.py
orcheo/nodes/telegram.py
orcheo/nodes/triggers.py
orcheo/nodes/wecom.py
orcheo/nodes/agent_tools/__init__.py
orcheo/nodes/agent_tools/registry.py
orcheo/nodes/agent_tools/tools.py
orcheo/nodes/conversational_search/__init__.py
orcheo/nodes/conversational_search/conversation.py
orcheo-0.17.1.dist-info/METADATA
orcheo-0.17.1.dist-info/WHEEL
orcheo-0.17.1.dist-info/entry_points.txt
orcheo-0.17.1.dist-info/licenses/LICENSE
orcheo-0.17.1.dist-info/RECORD
