Metadata-Version: 2.4
Name: orcheo
Version: 0.17.1
Summary: Add your description here
License-File: LICENSE
Requires-Python: >=3.12
Requires-Dist: agentensor>=0.0.4
Requires-Dist: aiosqlite>=0.22.0
Requires-Dist: croniter>=2.0.0
Requires-Dist: cryptography>=43.0.1
Requires-Dist: dynaconf>=3.2.4
Requires-Dist: fastapi>=0.104.0
Requires-Dist: fastmcp>=2.13.0.2
Requires-Dist: feedparser>=6.0.11
Requires-Dist: httpx>=0.28.1
Requires-Dist: langchain-community>=0.0.10
Requires-Dist: langchain-google-genai>=3.0.0
Requires-Dist: langchain-mcp-adapters>=0.2.1
Requires-Dist: langchain-openai>=0.0.5
Requires-Dist: langchain>=1.1.3
Requires-Dist: langgraph-checkpoint-postgres>=3.0.0
Requires-Dist: langgraph-checkpoint-sqlite>=3.0.0
Requires-Dist: langgraph>=1.0.5
Requires-Dist: mcp[cli]>=1.12.0
Requires-Dist: openai-chatkit>=1.4.0
Requires-Dist: openai>=1.0.0
Requires-Dist: opentelemetry-api>=1.26.0
Requires-Dist: opentelemetry-exporter-otlp>=1.26.0
Requires-Dist: opentelemetry-sdk>=1.26.0
Requires-Dist: pinecone-text>=0.11.0
Requires-Dist: pinecone>=8.0.0
Requires-Dist: psycopg[binary,pool]>=3.2.0
Requires-Dist: py-mini-racer>=0.6.0
Requires-Dist: pycryptodome>=3.20.0
Requires-Dist: pydantic>=2.4.2
Requires-Dist: pymongo>=4.13.2
Requires-Dist: python-dotenv>=1.0.0
Requires-Dist: python-telegram-bot>=22.0
Requires-Dist: restrictedpython>=7.2
Requires-Dist: selenium>=4.32.0
Requires-Dist: uvicorn>=0.24.0
Requires-Dist: websockets>=12.0
